donkit_ragops/__init__.py
donkit_ragops/__main__.py
donkit_ragops/agent/__init__.py
donkit_ragops/agent/agent.py
donkit_ragops/agent/local_tools/__init__.py
donkit_ragops/agent/local_tools/checklist_tools.py
donkit_ragops/agent/local_tools/project_tools.py
donkit_ragops/agent/local_tools/tools.py
donkit_ragops/agent/prompts.py
donkit_ragops/checklist_manager.py
donkit_ragops/cli.py
donkit_ragops/cli_helpers.py
donkit_ragops/command_palette.py
donkit_ragops/compose/services/docker-compose.yml
donkit_ragops/compose/templates/.env.template
donkit_ragops/compose/templates/README.md
donkit_ragops/config.py
donkit_ragops/credential_checker.py
donkit_ragops/db.py
donkit_ragops/display.py
donkit_ragops/enterprise/__init__.py
donkit_ragops/enterprise/analyzer.py
donkit_ragops/enterprise/auth.py
donkit_ragops/enterprise/config.py
donkit_ragops/enterprise/event_listener.py
donkit_ragops/enterprise/message_persister.py
donkit_ragops/enterprise/upload.py
donkit_ragops/history_manager.py
donkit_ragops/http_client.py
donkit_ragops/interactive_input.py
donkit_ragops/llm/__init__.py
donkit_ragops/llm/provider_factory.py
donkit_ragops/llm/providers/__init__.py
donkit_ragops/llm/providers/mock.py
donkit_ragops/logging_config.py
donkit_ragops/mcp/client.py
donkit_ragops/mcp/http_client.py
donkit_ragops/mcp/protocol.py
donkit_ragops/mcp/servers/chunker_server.py
donkit_ragops/mcp/servers/compose_manager_server.py
donkit_ragops/mcp/servers/donkit_ragops_mcp.py
donkit_ragops/mcp/servers/logs/evaluation.log
donkit_ragops/mcp/servers/planner_server.py
donkit_ragops/mcp/servers/rag_evaluation_server.py
donkit_ragops/mcp/servers/rag_query_server.py
donkit_ragops/mcp/servers/read_engine_server.py
donkit_ragops/mcp/servers/vectorstore_loader_server.py
donkit_ragops/mode.py
donkit_ragops/model_selector.py
donkit_ragops/prints.py
donkit_ragops/repl/__init__.py
donkit_ragops/repl/base.py
donkit_ragops/repl/command/airbyte.py
donkit_ragops/repl/commands.py
donkit_ragops/repl/enterprise_repl.py
donkit_ragops-0.5.2.dist-info/LICENSE
donkit_ragops-0.5.2.dist-info/METADATA
donkit_ragops-0.5.2.dist-info/WHEEL
donkit_ragops-0.5.2.dist-info/entry_points.txt
donkit_ragops-0.5.2.dist-info/RECORD
